django_simple_media_manager/__init__.py
django_simple_media_manager/admin.py
django_simple_media_manager/apps.py
django_simple_media_manager/urls.py
django_simple_media_manager/application/__init__.py
django_simple_media_manager/application/dependency/__init__.py
django_simple_media_manager/application/dependency/registry.py
django_simple_media_manager/domain/__init__.py
django_simple_media_manager/domain/command/__init__.py
django_simple_media_manager/domain/command/image.py
django_simple_media_manager/domain/repository/__init__.py
django_simple_media_manager/domain/repository/image.py
django_simple_media_manager/infrastructure/__init__.py
django_simple_media_manager/infrastructure/adapters/__init__.py
django_simple_media_manager/infrastructure/adapters/image.py
django_simple_media_manager/infrastructure/models/__init__.py
django_simple_media_manager/infrastructure/models/file.py
django_simple_media_manager/infrastructure/models/image.py
django_simple_media_manager/migrations/0001_initial.py
django_simple_media_manager/migrations/__init__.py
django_simple_media_manager/presentation/__init__.py
django_simple_media_manager/presentation/apis/__init__.py
django_simple_media_manager/presentation/apis/image.py
django_simple_media_manager/presentation/apis/serializers/__init__.py
django_simple_media_manager/presentation/apis/serializers/image.py
django_simple_media_manager-0.2.1.dist-info/METADATA
django_simple_media_manager-0.2.1.dist-info/WHEEL
django_simple_media_manager-0.2.1.dist-info/top_level.txt
django_simple_media_manager-0.2.1.dist-info/RECORD
